[
  {
    "title": "我党历史上的重要会议",
    "link": "https://mp.weixin.qq.com/s/Ydtld1x630Vo8gCAbrCPYg",
    "date": "2025-11-25",
    "description": "读党的历史，方知筚路蓝缕创业之艰，读党的历史，方知上下求索守业之困，读党的历史，方知不忘初心牢记使命兴业之难。"
  },
  {
    "title": "曹操诗选文选",
    "link": "https://mp.weixin.qq.com/s/8ZaYsn_qR4Ki9PUP-HRzeA",
    "date": "2025-11-25",
    "description": "往事越千年，魏武挥鞭，东临碣石有遗篇，萧瑟秋风今又是，换了人间。"
  },
  {
    "title": "东方之既白2020小记",
    "link": "https://mp.weixin.qq.com/s/cU3CLtZuiPB8WthZ5hEREA",
    "date": "2025-11-25",
    "description": "转眼，已然到了2021年，仿佛2020这一年走地格外的快。世界是因为疫情走地快，而我们，也许是因为东方之既白走地快。"
  },
  {
    "title": "秋夜",
    "link": "https://mp.weixin.qq.com/s/VsDNuCNJ-KVq0ekN22Tiqg",
    "date": "2025-11-25",
    "description": "原作于2013-10-11，于合肥。"
  },
  {
    "title": "云南六记",
    "link": "https://mp.weixin.qq.com/s/RYwn2Z8YTQplFtqfL0vWxw",
    "date": "2025-11-25",
    "description": "近日游云南昆明、大理、丽江、香格里拉四城，历时十天，有所见，有所闻，有所感，模仿《浮生六记》写下这篇《云南六记》，以娱视听，以记其事。"
  },
  {
    "title": "再见，科比·布莱恩特",
    "link": "https://mp.weixin.qq.com/s/De8vXRIYL7rqNa7GumQqgQ",
    "date": "2025-11-25",
    "description": "谨以此文，纪念我们的青春，科比·布莱恩特。"
  },
  {
    "title": "1997，乔布斯如何定位苹果的市场战略和价值观",
    "link": "https://mp.weixin.qq.com/s/dzL-5piH0Xt3WCiHZVJyeA",
    "date": "2025-11-25",
    "description": "1996，可能是苹果历史上最为艰难的一年。苹果的股价从91年的70美元暴跌到14美元，市场份额从80年代末的16%降到冰点4%，前任CEO试图寻求其他公司对苹果的收购，Mac系统也在封闭和授权其他硬件间徘徊不定。尔时的苹果，就像是一艘迷航的破船，四面漏水，却又不知路在何方。"
  }
]